{
	"info": {
		"_postman_id": "c2fbb821-0340-4921-9698-4fefb076d673",
		"name": "News Agregator",
		"description": "News agregator API",
		"schema": "https://schema.getpostman.com/json/collection/v2.1.0/collection.json",
		"_exporter_id": "9119505"
	},
	"item": [
		{
			"name": "User Preference",
			"item": [
				{
					"name": "Get Preferences",
					"request": {
						"method": "GET",
						"header": [
							{
								"key": "Authorization",
								"value": "Bearer {{token}}",
								"type": "text"
							}
						],
						"url": {
							"raw": "{{baseUrl}}/preferences",
							"host": [
								"{{baseUrl}}"
							],
							"path": [
								"preferences"
							]
						}
					},
					"response": [
						{
							"name": "Sample",
							"originalRequest": {
								"method": "GET",
								"header": [
									{
										"key": "Authorization",
										"value": "Bearer ",
										"type": "text"
									}
								],
								"url": {
									"raw": "/preferences",
									"path": [
										"preferences"
									]
								}
							},
							"status": "OK",
							"code": 200,
							"_postman_previewlanguage": null,
							"header": [
								{
									"key": "Host",
									"value": "127.0.0.1:8000"
								},
								{
									"key": "Connection",
									"value": "close"
								},
								{
									"key": "X-Powered-By",
									"value": "PHP/8.3.25"
								},
								{
									"key": "Cache-Control",
									"value": "no-cache, private"
								},
								{
									"key": "Date",
									"value": "Wed, 15 Oct 2025 08:32:43 GMT"
								},
								{
									"key": "Content-Type",
									"value": "application/json"
								},
								{
									"key": "Access-Control-Allow-Origin",
									"value": "*"
								}
							],
							"cookie": [],
							"body": "{\n    \"status\": \"success\",\n    \"data\": {\n        \"sources\": [\n            {\n                \"id\": 1,\n                \"name\": \"newsapi\"\n            },\n            {\n                \"id\": 2,\n                \"name\": \"nytimes\"\n            }\n        ],\n        \"categories\": [\n            {\n                \"id\": 5,\n                \"name\": \"Entertainment\"\n            }\n        ],\n        \"authors\": [\n            \"John Doe\",\n            \"Jane Smith\",\n            \"Mike Johnson\",\n            \"Sarah Williams\"\n        ]\n    }\n}"
						}
					]
				},
				{
					"name": "Update Preferences",
					"request": {
						"method": "PUT",
						"header": [
							{
								"key": "Authorization",
								"value": "Bearer {{token}}",
								"type": "text"
							}
						],
						"body": {
							"mode": "raw",
							"raw": "{\n    \"sources\": [1, 2]\n}",
							"options": {
								"raw": {
									"language": "json"
								}
							}
						},
						"url": {
							"raw": "{{baseUrl}}/preferences",
							"host": [
								"{{baseUrl}}"
							],
							"path": [
								"preferences"
							]
						}
					},
					"response": []
				},
				{
					"name": "Add Single Preference",
					"request": {
						"method": "POST",
						"header": [
							{
								"key": "Authorization",
								"value": "Bearer {{token}}",
								"type": "text"
							}
						],
						"body": {
							"mode": "raw",
							"raw": "{\n    \"source_id\": 3\n}",
							"options": {
								"raw": {
									"language": "json"
								}
							}
						},
						"url": {
							"raw": "{{baseUrl}}/preferences/add",
							"host": [
								"{{baseUrl}}"
							],
							"path": [
								"preferences",
								"add"
							]
						}
					},
					"response": [
						{
							"name": "Sample",
							"originalRequest": {
								"method": "POST",
								"header": [
									{
										"key": "Authorization",
										"value": "Bearer ",
										"type": "text"
									}
								],
								"body": {
									"mode": "raw",
									"raw": "{\n    \"source_id\": 3\n}",
									"options": {
										"raw": {
											"language": "json"
										}
									}
								},
								"url": {
									"raw": "/preferences/add",
									"path": [
										"preferences",
										"add"
									]
								}
							},
							"status": "OK",
							"code": 200,
							"_postman_previewlanguage": null,
							"header": [
								{
									"key": "Host",
									"value": "127.0.0.1:8000"
								},
								{
									"key": "Connection",
									"value": "close"
								},
								{
									"key": "X-Powered-By",
									"value": "PHP/8.3.25"
								},
								{
									"key": "Cache-Control",
									"value": "no-cache, private"
								},
								{
									"key": "Date",
									"value": "Wed, 15 Oct 2025 08:29:46 GMT"
								},
								{
									"key": "Content-Type",
									"value": "application/json"
								},
								{
									"key": "Access-Control-Allow-Origin",
									"value": "*"
								}
							],
							"cookie": [],
							"body": "{\n    \"status\": \"success\",\n    \"message\": \"Preference added successfully\"\n}"
						}
					]
				},
				{
					"name": "Remove Single Preference",
					"request": {
						"method": "DELETE",
						"header": [
							{
								"key": "Authorization",
								"value": "Bearer {{token}}",
								"type": "text"
							}
						],
						"body": {
							"mode": "raw",
							"raw": "{\n    \"source_id\": 3\n}",
							"options": {
								"raw": {
									"language": "json"
								}
							}
						},
						"url": {
							"raw": "{{baseUrl}}/preferences/remove",
							"host": [
								"{{baseUrl}}"
							],
							"path": [
								"preferences",
								"remove"
							]
						}
					},
					"response": [
						{
							"name": "Sample",
							"originalRequest": {
								"method": "DELETE",
								"header": [
									{
										"key": "Authorization",
										"value": "Bearer ",
										"type": "text"
									}
								],
								"body": {
									"mode": "raw",
									"raw": "{\n    \"source_id\": 3\n}",
									"options": {
										"raw": {
											"language": "json"
										}
									}
								},
								"url": {
									"raw": "/preferences/remove",
									"path": [
										"preferences",
										"remove"
									]
								}
							},
							"status": "OK",
							"code": 200,
							"_postman_previewlanguage": null,
							"header": [
								{
									"key": "Host",
									"value": "127.0.0.1:8000"
								},
								{
									"key": "Connection",
									"value": "close"
								},
								{
									"key": "X-Powered-By",
									"value": "PHP/8.3.25"
								},
								{
									"key": "Cache-Control",
									"value": "no-cache, private"
								},
								{
									"key": "Date",
									"value": "Wed, 15 Oct 2025 08:32:37 GMT"
								},
								{
									"key": "Content-Type",
									"value": "application/json"
								},
								{
									"key": "Access-Control-Allow-Origin",
									"value": "*"
								}
							],
							"cookie": [],
							"body": "{\n    \"status\": \"success\",\n    \"message\": \"Preference removed successfully\"\n}"
						}
					]
				},
				{
					"name": "Feed",
					"protocolProfileBehavior": {
						"disableBodyPruning": true
					},
					"request": {
						"method": "GET",
						"header": [
							{
								"key": "Authorization",
								"value": "Bearer {{token}}",
								"type": "text"
							}
						],
						"body": {
							"mode": "raw",
							"raw": ""
						},
						"url": {
							"raw": "{{baseUrl}}/feed",
							"host": [
								"{{baseUrl}}"
							],
							"path": [
								"feed"
							]
						}
					},
					"response": []
				}
			]
		},
		{
			"name": "Auth",
			"item": [
				{
					"name": "Login",
					"event": [
						{
							"listen": "test",
							"script": {
								"exec": [
									"pm.environment.set(\"token\", pm.response.json().access_token);"
								],
								"type": "text/javascript",
								"packages": {},
								"requests": {}
							}
						}
					],
					"request": {
						"auth": {
							"type": "apikey",
							"apikey": [
								{
									"key": "value",
									"value": "{{apiKey}}",
									"type": "string"
								},
								{
									"key": "key",
									"value": "x-api-key",
									"type": "string"
								}
							]
						},
						"method": "POST",
						"header": [],
						"body": {
							"mode": "raw",
							"raw": "{\n    \"email\": \"test@example.com\",\n    \"password\": \"password123\"\n}",
							"options": {
								"raw": {
									"language": "json"
								}
							}
						},
						"url": {
							"raw": "{{baseUrl}}/login",
							"host": [
								"{{baseUrl}}"
							],
							"path": [
								"login"
							]
						}
					},
					"response": []
				},
				{
					"name": "Register",
					"request": {
						"auth": {
							"type": "apikey",
							"apikey": [
								{
									"key": "value",
									"value": "{{apiKey}}",
									"type": "string"
								},
								{
									"key": "key",
									"value": "x-api-key",
									"type": "string"
								}
							]
						},
						"method": "POST",
						"header": [],
						"body": {
							"mode": "raw",
							"raw": "{\n    \"name\": \"dumebi kachi\",\n    \"email\": \"test2@example.com\",\n    \"password\": \"password123\",\n    \"password_confirmation\": \"password123\"\n}",
							"options": {
								"raw": {
									"language": "json"
								}
							}
						},
						"url": {
							"raw": "{{baseUrl}}/register",
							"host": [
								"{{baseUrl}}"
							],
							"path": [
								"register"
							]
						}
					},
					"response": []
				},
				{
					"name": "Me",
					"request": {
						"auth": {
							"type": "apikey",
							"apikey": [
								{
									"key": "value",
									"value": "{{apiKey}}",
									"type": "string"
								},
								{
									"key": "key",
									"value": "x-api-key",
									"type": "string"
								}
							]
						},
						"method": "GET",
						"header": [
							{
								"key": "Authorization",
								"value": "Bearer {{token}}",
								"type": "text"
							}
						],
						"url": {
							"raw": "{{baseUrl}}/me",
							"host": [
								"{{baseUrl}}"
							],
							"path": [
								"me"
							]
						}
					},
					"response": []
				},
				{
					"name": "Logout",
					"request": {
						"method": "POST",
						"header": [
							{
								"key": "Authorization",
								"value": "Bearer {{token}}",
								"type": "text"
							}
						],
						"url": {
							"raw": "{{baseUrl}}/logout",
							"host": [
								"{{baseUrl}}"
							],
							"path": [
								"logout"
							]
						}
					},
					"response": []
				}
			]
		},
		{
			"name": "Get Articles",
			"request": {
				"auth": {
					"type": "noauth"
				},
				"method": "GET",
				"header": [],
				"url": {
					"raw": "{{baseUrl}}/articles?source=3&from=2025-10-12&to=2025-10-12",
					"host": [
						"{{baseUrl}}"
					],
					"path": [
						"articles"
					],
					"query": [
						{
							"key": "search",
							"value": "Badenoch",
							"disabled": true
						},
						{
							"key": "source",
							"value": "3"
						},
						{
							"key": "from",
							"value": "2025-10-12"
						},
						{
							"key": "to",
							"value": "2025-10-12"
						}
					]
				}
			},
			"response": []
		},
		{
			"name": "Get Categories",
			"request": {
				"auth": {
					"type": "apikey",
					"apikey": [
						{
							"key": "value",
							"value": "{{apiKey}}",
							"type": "string"
						},
						{
							"key": "key",
							"value": "x-api-key",
							"type": "string"
						}
					]
				},
				"method": "GET",
				"header": [
					{
						"key": "Accept",
						"value": "application/json",
						"type": "text"
					}
				],
				"url": {
					"raw": "{{baseUrl}}/categories",
					"host": [
						"{{baseUrl}}"
					],
					"path": [
						"categories"
					]
				}
			},
			"response": []
		},
		{
			"name": "Get Sources",
			"request": {
				"method": "GET",
				"header": [],
				"url": {
					"raw": "{{baseUrl}}/sources",
					"host": [
						"{{baseUrl}}"
					],
					"path": [
						"sources"
					]
				}
			},
			"response": []
		}
	],
	"auth": {
		"type": "apikey",
		"apikey": [
			{
				"key": "key",
				"value": "x-api-key",
				"type": "string"
			},
			{
				"key": "value",
				"value": "{{apiKey}}",
				"type": "string"
			}
		]
	},
	"event": [
		{
			"listen": "prerequest",
			"script": {
				"type": "text/javascript",
				"packages": {},
				"requests": {},
				"exec": [
					""
				]
			}
		},
		{
			"listen": "test",
			"script": {
				"type": "text/javascript",
				"packages": {},
				"requests": {},
				"exec": [
					""
				]
			}
		}
	]
}